MANIFEST.in
README.md
setup.cfg
setup.py
chana/__init__.py
chana/lemmatizer.py
chana/ner.py
chana/pos_tagger.py
chana/syllabificator.py
chana.egg-info/PKG-INFO
chana.egg-info/SOURCES.txt
chana.egg-info/dependency_links.txt
chana.egg-info/top_level.txt
chana/files/lemmatizer/shipibo_knn_model.pkl
chana/files/lemmatizer/shipibo_suffixes.dat
chana/files/ner/crf_ner.crfsuite
chana/files/ner/loc_esp_s.dat
chana/files/ner/org_esp_s.dat
chana/files/ner/per_esp_s.dat
chana/files/pos_tagger/shipibo_svm_model.pkl