Metadata-Version: 1.1
Name: chana
Version: 0.9
Summary: A library of NLP tools for the shipibo-konibo language
Home-page: https://github.com/iapucp/chana-library
Author: Jose Pereira
Author-email: jpereira@pucp.edu.pe
License: MIT
Project-URL: Main Page, https://chana.inf.pucp.edu.pe
Keywords: nlp shipibo development
Platform: UNKNOWN
Classifier: Development Status :: 4 - Beta
Classifier: License :: OSI Approved :: MIT License
Classifier: Programming Language :: Python :: 3
Classifier: Programming Language :: Python :: 3.4
Classifier: Programming Language :: Python :: 3.5
Classifier: Programming Language :: Python :: 3.6
